davesradio/davesradio.py
davesradio-0.2.dist-info/AUTHORS.rst
davesradio-0.2.dist-info/LICENSE
davesradio-0.2.dist-info/METADATA
davesradio-0.2.dist-info/WHEEL
davesradio-0.2.dist-info/top_level.txt
davesradio-0.2.dist-info/RECORD
