Metadata-Version: 2.1
Name: davesradio
Version: 0.2
Summary: Play the newest episode podcasts from my feed
Home-page: UNKNOWN
Author: David Mekonnen Rønn
Author-email: gh@v1d.dk
License: UNKNOWN
Platform: UNKNOWN
